Day_1/counter/good_counter.v
module good_counter (
    input clk,
    input reset,
    output reg [1:0] cnt
);

wire comp;

assign comp = (cnt == 2'b10);

always @(posedge clk, posedge reset)
begin
    if(reset)
        cnt <= 2'b00;
    else if(comp)
        cnt <= 2'b00;
    else
        cnt <= cnt + 1;
end

endmodule

Day_1/counter/tb_good_counter.v
`timescale 1ns/1ps

module tb_good_counter;

reg clk;
reg reset;
wire [1:0] cnt;

good_counter uut (
    .clk(clk),
    .reset(reset),
    .cnt(cnt)
);

initial begin
    $dumpfile("tb_good_counter.vcd");
    $dumpvars(0, tb_good_counter);

    clk = 0;
    reset = 1;

    #20;
    reset = 0;

    #100;
    $finish;
end

always #5 clk = ~clk;

endmodule

Day_1/counter/tb_good_counter.vcd
$date
	Sat Aug  8 13:55:39 2026
$end
$version
	Icarus Verilog
$end
$timescale
	1ps
$end
$scope module tb_good_counter $end
$var wire 2 ! cnt [1:0] $end
$var reg 1 " clk $end
$var reg 1 # reset $end
$scope module uut $end
$var wire 1 " clk $end
$var wire 1 # reset $end
$var wire 1 $ comp $end
$var reg 2 % cnt [1:0] $end
$upscope $end
$upscope $end
$enddefinitions $end
$comment Show the parameter values. $end
$dumpall
$end
#0
$dumpvars
b0 %
0$
1#
0"
b0 !
$end
#5000
1"
#10000
0"
#15000
1"
#20000
0"
0#
#25000
b1 !
b1 %
1"
#30000
0"
#35000
1$
b10 !
b10 %
1"
#40000
0"
#45000
0$
b0 !
b0 %
1"
#50000
0"
#55000
b1 !
b1 %
1"
#60000
0"
#65000
1$
b10 !
b10 %
1"
#70000
0"
#75000
0$
b0 !
b0 %
1"
#80000
0"
#85000
b1 !
b1 %
1"
#90000
0"
#95000
1$
b10 !
b10 %
1"
#100000
0"
#105000
0$
b0 !
b0 %
1"
#110000
0"
#115000
b1 !
b1 %
1"
